LICENSE
LICENSE_BOOTSTRAP_ICONS
MANIFEST.in
README.md
pyproject.toml
setup.cfg
setup.py
request_filters/__init__.py
request_filters/actions.py
request_filters/admin.py
request_filters/apps.py
request_filters/checks.py
request_filters/middleware.py
request_filters/options.py
request_filters/signals.py
request_filters/tests.py
request_filters/util.py
request_filters/wagtail_hooks.py
request_filters.egg-info/PKG-INFO
request_filters.egg-info/SOURCES.txt
request_filters.egg-info/dependency_links.txt
request_filters.egg-info/requires.txt
request_filters.egg-info/top_level.txt
request_filters/migrations/0001_initial.py
request_filters/migrations/0002_alter_filter_options_alter_filter_filter_type_and_more.py
request_filters/migrations/0003_filteredrequest.py
request_filters/migrations/0004_filteredrequest_response_info.py
request_filters/migrations/0005_alter_filteredrequest_options_and_more.py
request_filters/migrations/0006_alter_filteredrequest_options.py
request_filters/migrations/0007_alter_filter_filter_type.py
request_filters/migrations/__init__.py
request_filters/migrations/__pycache__/0001_initial.cpython-311.pyc
request_filters/migrations/__pycache__/0002_alter_filter_options_alter_filter_filter_type_and_more.cpython-311.pyc
request_filters/migrations/__pycache__/0003_filteredrequest.cpython-311.pyc
request_filters/migrations/__pycache__/0004_filteredrequest_response_info.cpython-311.pyc
request_filters/migrations/__pycache__/0005_alter_filteredrequest_options_and_more.cpython-311.pyc
request_filters/migrations/__pycache__/0006_alter_filteredrequest_options.cpython-311.pyc
request_filters/migrations/__pycache__/0007_alter_filter_filter_type.cpython-311.pyc
request_filters/migrations/__pycache__/__init__.cpython-311.pyc
request_filters/models/__init__.py
request_filters/models/filters.py
request_filters/models/requests.py
request_filters/models/settings.py
request_filters/static/request_filters/admin/chart.js
request_filters/static/request_filters/admin/chart_view.js
request_filters/static/request_filters/admin/request_filters.css
request_filters/templates/request_filters/chart_view.html
