Metadata-Version: 2.1
Name: request_filters
Version: 1.4.6
Summary: A firewall for your wagtail application. It allows you to filter requests based on IP, User-Agent, URL and Country.
Home-page: https://github.com/Nigel2392/request_filters
Author: Nigel
Author-email: nigel@goodadvice.it
License: GPL-3.0-only
Classifier: Environment :: Web Environment
Classifier: Framework :: Django
Classifier: Framework :: Django :: 4.2
Classifier: Intended Audience :: Developers
Classifier: License :: OSI Approved :: GNU General Public License v3 or later (GPLv3+)
Classifier: Operating System :: OS Independent
Classifier: Programming Language :: Python
Classifier: Programming Language :: Python :: 3
Classifier: Programming Language :: Python :: 3 :: Only
Classifier: Programming Language :: Python :: 3.8
Classifier: Programming Language :: Python :: 3.9
Classifier: Topic :: Internet :: WWW/HTTP
Classifier: Topic :: Internet :: WWW/HTTP :: Dynamic Content
Requires-Python: >=3.8
License-File: LICENSE
License-File: LICENSE_BOOTSTRAP_ICONS
Requires-Dist: Django>=4.2
Requires-Dist: Wagtail>=5.0
Requires-Dist: django-filter>=21.1
